[{
    "filename": "00_01",
    "title": "Using Git with Visual Studio Code" }
,{
    "filename": "01_01",
    "title": "Requirements" }
,{
    "filename": "01_02",
    "title": "Project Setup" }
,{
    "filename": "01_03",
    "title": "Useful Extensions" }
,{
    "filename": "02_01",
    "title": "Built-in Terminals" }
,{
    "filename": "02_02",
    "title": "Command Palette" }
,{
    "filename": "02_03",
    "title": "Status Bar" }
,{
    "filename": "02_04",
    "title": "Explorer/Editor" }
,{
    "filename": "02_05",
    "title": "Editor" }
,{
    "filename": "03_01",
    "title": "Setting up a Repo" }
,{
    "filename": "03_02",
    "title": "Staging and Committing" }
,{
    "filename": "03_03",
    "title": "Source Control" }
,{
    "filename": "03_04",
    "title": "Diffing" }
,{
    "filename": "03_05",
    "title": "VS Code Logs" }
,{
    "filename": "03_06",
    "title": "Copilot" }
,{
    "filename": "04_01",
    "title": "Merge Conflicts" }
,{
    "filename": "04_02",
    "title": "Pull Requests" }
,{
    "filename": "04_03",
    "title": "Issues" }
,{
    "filename": "04_04",
    "title": "CodeSpaces" }
,{
    "filename": "04_05",
    "title": "Remote Explorer" }
,{
    "filename": "05_01",
    "title": "Git Graph" }
,{
    "filename": "05_02",
    "title": "Git History" }
,{
    "filename": "05_03",
    "title": "Git Lens" }
,{
    "filename": "06_01",
    "title": "Going Further" }
,{
    "filename": "demo",
    "title": "Opinionated Reveal.js" }
,{
    "filename": "slides",
    "title": "" }
]